{"claims":[{"f":"casualties.deaths","q":"Fatalities:             0","v":0},{"f":"casualties.injuries","q":"Injuries:               2","v":2},{"f":"ef_rating","q":"Rating:                 EF3","v":"EF3"},{"f":"ext:location.lat","q":"Start Lat/Lon:          39.1904 / -88.7975","v":39.1904},{"f":"ext:location.lon","q":"Start Lat/Lon:          39.1904 / -88.7975","v":-88.7975},{"f":"ext:location.name","q":"Start Location:         1 WNW Beecher City / Effingham County / IL","v":"1 WNW Beecher City / Effingham County / IL"},{"f":"ext:path.end_geo","q":"End Lat/Lon:            39.0983 / -88.2232","v":"geo:dncq2m"},{"f":"ext:path.end_time","q":"End Date:               06/17/2026\nEnd Time:               08:34 PM CDT","v":"2026-06-17T20:34-05:00"},{"f":"ext:path.length_mi","q":"Path Length /statute/:  31.83 miles","v":31.83},{"f":"ext:path.width_max_yd","q":"Path Width /maximum/:   500 yards","v":500},{"f":"ext:peak_wind_mph","q":"Estimated Peak Wind:    150 mph","v":150},{"f":"what","q":"NWS Damage Survey for 6/17/2026 Tornado Event","v":"disaster.tornado"},{"f":"when","q":"Start Date:             06/17/2026\nStart Time:             07:56 PM CDT","v":"2026-06-17T19:56-05:00"},{"f":"where","q":"Start Lat/Lon:          39.1904 / -88.7975","v":"geo:dnbygq"}],"pure":"v0.1.1","source":{"retrievedAt":"2026-07-19T12:51:59Z","sha256":"86d54c09a61ce939dac65172f6f2ff196aad654b88bb673eb76a275446d76128","url":"https://mesonet.agron.iastate.edu/api/1/nwstext/202606250931-KILX-NOUS43-PNSILX"}}
